protmapper/__init__.py
protmapper/api.py
protmapper/cli.py
protmapper/curated_site_map.csv
protmapper/phosphosite_client.py
protmapper/refseq_client.py
protmapper/resources.py
protmapper/uniprot_client.py
protmapper/rest_api/__init__.py
protmapper/rest_api/__main__.py
protmapper/rest_api/api.py
protmapper/tests/test_cache_read.pkl
protmapper-0.0.29.dist-info/LICENSE
protmapper-0.0.29.dist-info/METADATA
protmapper-0.0.29.dist-info/WHEEL
protmapper-0.0.29.dist-info/entry_points.txt
protmapper-0.0.29.dist-info/top_level.txt
protmapper-0.0.29.dist-info/RECORD
