Metadata-Version: 2.1
Name: protmapper
Version: 0.0.29
Summary: Map protein sites to human reference sequence.
Home-page: https://github.com/indralab/protmapper
Author: John A. Bachman
Author-email: john_bachman@hms.harvard.edu
Keywords: protein,proteomics,sequence,alignment,assembly,post-translational,modification
Classifier: Development Status :: 4 - Beta
Classifier: Environment :: Console
Classifier: Intended Audience :: Science/Research
Classifier: License :: OSI Approved :: BSD License
Classifier: Operating System :: OS Independent
Classifier: Programming Language :: Python :: 3
Classifier: Topic :: Scientific/Engineering :: Bio-Informatics
License-File: LICENSE
Requires-Dist: requests
Requires-Dist: boto3
Requires-Dist: pystow (>=0.1.0)
Provides-Extra: rest_api
Requires-Dist: flask ; extra == 'rest_api'
Requires-Dist: flask-cors ; extra == 'rest_api'
